ansibledoctor/__init__.py
ansibledoctor/__main__.py
ansibledoctor/cli/__init__.py
ansibledoctor/cli/__main__.py
ansibledoctor/cli/collection.py
ansibledoctor/cli/linkcheck.py
ansibledoctor/cli/project.py
ansibledoctor/cli/schema.py
ansibledoctor/config/__init__.py
ansibledoctor/config/language.py
ansibledoctor/config/loader.py
ansibledoctor/config/models.py
ansibledoctor/config/theme.py
ansibledoctor/config/validator.py
ansibledoctor/context/__init__.py
ansibledoctor/context/detector.py
ansibledoctor/exceptions/__init__.py
ansibledoctor/exceptions/aggregator.py
ansibledoctor/exceptions/codes.py
ansibledoctor/exceptions/recovery.py
ansibledoctor/exceptions.py
ansibledoctor/generator/__init__.py
ansibledoctor/generator/cascading_loader.py
ansibledoctor/generator/collection_generator.py
ansibledoctor/generator/css_injector.py
ansibledoctor/generator/engine.py
ansibledoctor/generator/errors.py
ansibledoctor/generator/filters.py
ansibledoctor/generator/indexes.py
ansibledoctor/generator/loaders.py
ansibledoctor/generator/models.py
ansibledoctor/generator/multi_language.py
ansibledoctor/generator/output_format.py
ansibledoctor/generator/project_generator.py
ansibledoctor/generator/protocols.py
ansibledoctor/generator/renderers/__init__.py
ansibledoctor/generator/renderers/html.py
ansibledoctor/generator/renderers/markdown.py
ansibledoctor/generator/renderers/rst.py
ansibledoctor/generator/renderers.py
ansibledoctor/generator/templates/html/_breadcrumb.j2
ansibledoctor/generator/templates/html/_siblings.j2
ansibledoctor/generator/templates/html/collection.j2
ansibledoctor/generator/templates/html/index/tags.j2
ansibledoctor/generator/templates/html/project.j2
ansibledoctor/generator/templates/html/role.j2
ansibledoctor/generator/templates/markdown/_breadcrumb.j2
ansibledoctor/generator/templates/markdown/_siblings.j2
ansibledoctor/generator/templates/markdown/collection.j2
ansibledoctor/generator/templates/markdown/index/diagram.j2
ansible_doctor_enhanced-0.14.1.dist-info/entry_points.txt
ansible_doctor_enhanced-0.14.1.dist-info/licenses/LICENSE
ansible_doctor_enhanced-0.14.1.dist-info/licenses/NOTICE
ansible_doctor_enhanced-0.14.1.dist-info/METADATA
ansible_doctor_enhanced-0.14.1.dist-info/WHEEL
ansible_doctor_enhanced-0.14.1.dist-info/RECORD
