Metadata-Version: 2.4
Name: ansible-doctor-enhanced
Version: 0.14.1
Summary: Enhanced Ansible role documentation generator with annotation support, logging, error handling, and reporting
License: Apache-2.0
License-File: LICENSE
License-File: NOTICE
Keywords: ansible,documentation,parser,roles,annotations
Author: Cédric Thédrez
Author-email: kamicth@gmail.com
Requires-Python: >=3.11,<4.0
Classifier: Development Status :: 3 - Alpha
Classifier: Intended Audience :: Developers
Classifier: License :: OSI Approved :: Apache Software License
Classifier: Programming Language :: Python :: 3
Classifier: Programming Language :: Python :: 3.11
Classifier: Programming Language :: Python :: 3.12
Classifier: Programming Language :: Python :: 3.13
Classifier: Programming Language :: Python :: 3.14
Requires-Dist: ansible (<12.0.0)
Requires-Dist: ansible-core (>=2.14,<2.18)
Requires-Dist: ansible-creator (>=25.12.0,<26.0.0)
Requires-Dist: babel (>=2.17.0,<3.0.0)
Requires-Dist: beautifulsoup4 (>=4.11,<5.0)
Requires-Dist: click (>=8.1.0,<9.0.0)
Requires-Dist: jinja2 (>=3.1.0,<4.0.0)
Requires-Dist: jsonschema (>=4.0,<5.0)
Requires-Dist: packaging (>=24.0,<25.0)
Requires-Dist: pathspec (>=0.12.0,<0.13.0)
Requires-Dist: pydantic (>=2.0,<3.0)
Requires-Dist: pyyaml (>=6.0.3,<7.0.0)
Requires-Dist: requests (>=2.28,<3.0)
Requires-Dist: ruamel-yaml (>=0.18.0,<0.19.0)
Requires-Dist: structlog (>=24.0.0,<25.0.0)
Requires-Dist: watchdog (>=6.0.0,<7.0.0)
Project-URL: Homepage, https://github.com/K4M1coder/ansible-doctor-enhanced
Project-URL: Repository, https://github.com/K4M1coder/ansible-doctor-enhanced
